LICENSE
MANIFEST.in
README.md
requirements.txt
setup.py
nf_modules/__init__.py
nf_modules/cli.py
nf_modules/compile_reads_table.py
nf_modules/fetch.py
nf_modules/list.py
nf_modules.egg-info/PKG-INFO
nf_modules.egg-info/SOURCES.txt
nf_modules.egg-info/dependency_links.txt
nf_modules.egg-info/entry_points.txt
nf_modules.egg-info/requires.txt
nf_modules.egg-info/top_level.txt