Metadata-Version: 2.4
Name: nf-modules
Version: 0.2.2
Summary: Nextflow bioinformatics modules
Author: Josh L. Espinoza
Requires-Python: >=3.6
License-File: LICENSE
Requires-Dist: pandas>=2.1.0
Requires-Dist: PyYAML>=6.0
Dynamic: author
Dynamic: license-file
Dynamic: requires-dist
Dynamic: requires-python
Dynamic: summary
